volttron_openadr_ven/__init__.py
volttron_openadr_ven/agent.py
volttron_openadr_ven/constants.py
volttron_openadr_ven/volttron_openadr_client.py
volttron_openadr_ven-1.0.0.dist-info/LICENSE
volttron_openadr_ven-1.0.0.dist-info/WHEEL
volttron_openadr_ven-1.0.0.dist-info/METADATA
volttron_openadr_ven-1.0.0.dist-info/RECORD
